superfile/__init__.py
superfile/amazon_simple_storage_service.py
superfile/google_cloud_storage.py
superfile/interfaces.py
superfile/local_storage.py
superfile/local_storage_test.py
superfile/superfile.py
superfile-0.0.7.dist-info/licenses/LICENSE.md
superfile-0.0.7.dist-info/METADATA
superfile-0.0.7.dist-info/WHEEL
superfile-0.0.7.dist-info/top_level.txt
superfile-0.0.7.dist-info/RECORD
