Metadata-Version: 2.4
Name: superfile
Version: 0.0.7
Summary: File-like interface for cloud block storage
Author: Fresho Dev
License: MIT License
Classifier: Programming Language :: Python :: 3
Classifier: License :: OSI Approved :: MIT License
Classifier: Operating System :: OS Independent
License-File: LICENSE.md
Requires-Dist: boto3
Requires-Dist: boto3-stubs[essential]
Requires-Dist: google-cloud-storage
Dynamic: license-file
